<?xml version="1.0" encoding="UTF-8" ?>
<!DOCTYPE mapper PUBLIC "-//mybatis.org//DTD Mapper 3.0//EN" "http://mybatis.org/dtd/mybatis-3-mapper.dtd" >
<mapper namespace="com.zgss.grib.gribdata.mapper.Relative_humidityMapper" >
  <resultMap id="BaseResultMap" type="com.zgss.grib.gribdata.entity.Relative_humidity" >
    <!--
      WARNING - @mbggenerated
      This element is automatically generated by MyBatis Generator, do not modify.
    -->
    <id column="refTime" property="reftime" jdbcType="TIMESTAMP" />
    <id column="surfaceValue" property="surfacevalue" jdbcType="INTEGER" />
    <result column="lon" property="lon" jdbcType="DOUBLE" />
    <result column="lat" property="lat" jdbcType="DOUBLE" />
    <result column="value" property="value" jdbcType="DOUBLE" />
  </resultMap>
  <sql id="Base_Column_List" >
    <!--
      WARNING - @mbggenerated
      This element is automatically generated by MyBatis Generator, do not modify.
    -->
    "refTime", "surfaceValue", lon, lat, value
  </sql>
  <select id="selectByPrimaryKey" resultMap="BaseResultMap" parameterType="com.zgss.grib.gribdata.entity.Relative_humidityKey" >
    <!--
      WARNING - @mbggenerated
      This element is automatically generated by MyBatis Generator, do not modify.
    -->
    select 
    <include refid="Base_Column_List" />
    from "Relative_humidity"
    where "refTime" = #{reftime,jdbcType=TIMESTAMP}
      and "surfaceValue" = #{surfacevalue,jdbcType=INTEGER}
  </select>
  <delete id="deleteByPrimaryKey" parameterType="com.zgss.grib.gribdata.entity.Relative_humidityKey" >
    <!--
      WARNING - @mbggenerated
      This element is automatically generated by MyBatis Generator, do not modify.
    -->
    delete from "Relative_humidity"
    where "refTime" = #{reftime,jdbcType=TIMESTAMP}
      and "surfaceValue" = #{surfacevalue,jdbcType=INTEGER}
  </delete>
  <insert id="insert" parameterType="com.zgss.grib.gribdata.entity.Relative_humidity" >
    <!--
      WARNING - @mbggenerated
      This element is automatically generated by MyBatis Generator, do not modify.
    -->
    insert into "Relative_humidity" ("refTime", "surfaceValue", lon,
      lat, value)
    values (#{reftime,jdbcType=TIMESTAMP}, #{surfacevalue,jdbcType=INTEGER}, #{lon,jdbcType=DOUBLE}, 
      #{lat,jdbcType=DOUBLE}, #{value,jdbcType=DOUBLE})
  </insert>
  <insert id="insertSelective" parameterType="com.zgss.grib.gribdata.entity.Relative_humidity" >
    <!--
      WARNING - @mbggenerated
      This element is automatically generated by MyBatis Generator, do not modify.
    -->
    insert into "Relative_humidity"
    <trim prefix="(" suffix=")" suffixOverrides="," >
      <if test="reftime != null" >
        "refTime",
      </if>
      <if test="surfacevalue != null" >
        "surfaceValue",
      </if>
      <if test="lon != null" >
        lon,
      </if>
      <if test="lat != null" >
        lat,
      </if>
      <if test="value != null" >
        value,
      </if>
    </trim>
    <trim prefix="values (" suffix=")" suffixOverrides="," >
      <if test="reftime != null" >
        #{reftime,jdbcType=TIMESTAMP},
      </if>
      <if test="surfacevalue != null" >
        #{surfacevalue,jdbcType=INTEGER},
      </if>
      <if test="lon != null" >
        #{lon,jdbcType=DOUBLE},
      </if>
      <if test="lat != null" >
        #{lat,jdbcType=DOUBLE},
      </if>
      <if test="value != null" >
        #{value,jdbcType=DOUBLE},
      </if>
    </trim>
  </insert>
  <update id="updateByPrimaryKeySelective" parameterType="com.zgss.grib.gribdata.entity.Relative_humidity" >
    <!--
      WARNING - @mbggenerated
      This element is automatically generated by MyBatis Generator, do not modify.
    -->
    update "Relative_humidity"
    <set >
      <if test="lon != null" >
        lon = #{lon,jdbcType=DOUBLE},
      </if>
      <if test="lat != null" >
        lat = #{lat,jdbcType=DOUBLE},
      </if>
      <if test="value != null" >
        value = #{value,jdbcType=DOUBLE},
      </if>
    </set>
    where "refTime" = #{reftime,jdbcType=TIMESTAMP}
      and "surfaceValue" = #{surfacevalue,jdbcType=INTEGER}
  </update>
  <update id="updateByPrimaryKey" parameterType="com.zgss.grib.gribdata.entity.Relative_humidity" >
    <!--
      WARNING - @mbggenerated
      This element is automatically generated by MyBatis Generator, do not modify.
    -->
    update "Relative_humidity"
    set lon = #{lon,jdbcType=DOUBLE},
      lat = #{lat,jdbcType=DOUBLE},
      value = #{value,jdbcType=DOUBLE}
    where "refTime" = #{reftime,jdbcType=TIMESTAMP}
      and "surfaceValue" = #{surfacevalue,jdbcType=INTEGER}
  </update>

  <select id="countByPrimaryKey" resultType="int" parameterType="com.zgss.grib.gribdata.entity.Relative_humidityKey" >
    <!--
      WARNING - @mbggenerated
      This element is automatically generated by MyBatis Generator, do not modify.
    -->
    select
    count(1)
    from "Relative_humidity"
    where "refTime" = #{reftime,jdbcType=TIMESTAMP}
    and "surfaceValue" = #{surfacevalue,jdbcType=INTEGER}
  </select>

  <insert id="insertBatch">
    insert into "Relative_humidity" ("refTime", "surfaceValue", lon,lat, value)
    values
    <foreach collection="list" item="item" index="index"
             separator=",">
      (#{item.reftime,jdbcType=TIMESTAMP}, #{item.surfacevalue,jdbcType=INTEGER}, #{item.lon,jdbcType=DOUBLE},
      #{item.lat,jdbcType=DOUBLE}, #{item.value,jdbcType=DOUBLE})
    </foreach>
  </insert>
</mapper>